data_go_mcp/presidential_speeches/__init__.py
data_go_mcp/presidential_speeches/api_client.py
data_go_mcp/presidential_speeches/models.py
data_go_mcp/presidential_speeches/server.py
data_go_mcp_presidential_speeches-0.1.0.dist-info/METADATA
data_go_mcp_presidential_speeches-0.1.0.dist-info/WHEEL
data_go_mcp_presidential_speeches-0.1.0.dist-info/entry_points.txt
data_go_mcp_presidential_speeches-0.1.0.dist-info/licenses/LICENSE
data_go_mcp_presidential_speeches-0.1.0.dist-info/RECORD
